vidhi/__init__.py
vidhi/base_poly_config.py
vidhi/cli.py
vidhi/cli_completion.py
vidhi/cli_parser.py
vidhi/constants.py
vidhi/frozen_dataclass.py
vidhi/schema.py
vidhi/types.py
vidhi/utils.py
vidhi/flat_dataclass/__init__.py
vidhi/flat_dataclass/cli.py
vidhi/flat_dataclass/core.py
vidhi/flat_dataclass/explosion.py
vidhi/flat_dataclass/reconstruction.py
vidhi/flat_dataclass/state.py
vidhi/flat_dataclass/validation.py
vidhi-0.1.0.dist-info/licenses/LICENSE
vidhi-0.1.0.dist-info/METADATA
vidhi-0.1.0.dist-info/WHEEL
vidhi-0.1.0.dist-info/top_level.txt
vidhi-0.1.0.dist-info/RECORD
