Metadata-Version: 2.4
Name: vidhi
Version: 0.1.0
Summary: Configuration management system for complex systems
Author-email: Vajra Team <team@project-vajra.org>
Maintainer-email: Vajra Team <team@project-vajra.org>
License: Apache-2.0
Project-URL: Homepage, https://github.com/project-vajra/vidhi
Project-URL: Documentation, https://project-vajra.github.io/vidhi
Project-URL: Bug Tracker, https://github.com/project-vajra/vidhi/issues
Keywords: config,configuration,dataclass,cli,yaml,polymorphic,immutable,frozen
Classifier: Development Status :: 3 - Alpha
Classifier: Intended Audience :: Developers
Classifier: License :: OSI Approved :: Apache Software License
Classifier: Operating System :: OS Independent
Classifier: Programming Language :: Python :: 3
Classifier: Programming Language :: Python :: 3.12
Classifier: Topic :: Software Development :: Libraries :: Application Frameworks
Requires-Python: >=3.12
License-File: LICENSE
Requires-Dist: pyyaml>=6.0
Provides-Extra: dev
Requires-Dist: pytest>=7.4.0; extra == "dev"
Requires-Dist: pytest-cov; extra == "dev"
Requires-Dist: black>=23.0.0; extra == "dev"
Requires-Dist: isort>=5.12.0; extra == "dev"
Requires-Dist: autoflake; extra == "dev"
Requires-Dist: codespell; extra == "dev"
Requires-Dist: pyright>=1.1.300; extra == "dev"
Requires-Dist: pre-commit>=3.0.0; extra == "dev"
Requires-Dist: build>=1.0.0; extra == "dev"
Requires-Dist: sphinx>=7.0; extra == "dev"
Requires-Dist: furo; extra == "dev"
Requires-Dist: sphinx-copybutton; extra == "dev"
Requires-Dist: sphinx-autobuild; extra == "dev"
Dynamic: license-file
